Graf/__init__.py
Graf/Algorithm/__init__.py
Graf/Algorithm/dijkstra.py
Graf/Algorithm/euler.py
Graf/Algorithm/floyd_warshall.py
Graf/Matrix/Adjacency_matrix.py
Graf/Matrix/Incidence_matrix.py
Graf/Matrix/Vis_matrix.py
Graf/Matrix/__init__.py
Graf_Lab_4_Py-1.0.3.dist-info/LICENSE.txt
Graf_Lab_4_Py-1.0.3.dist-info/METADATA
Graf_Lab_4_Py-1.0.3.dist-info/WHEEL
Graf_Lab_4_Py-1.0.3.dist-info/top_level.txt
Graf_Lab_4_Py-1.0.3.dist-info/RECORD
