Metadata-Version: 2.1
Name: Graf_Lab_4_Py
Version: 1.0.3
Summary: Библиотека для работы с графами и алгоритмами на них.
Home-page: https://github.com/DianaSadova/Graf
Author: Sadova Diana, Zhukova Arina
Author-email: grnshinnosha@gmail.com,arichka2005@yandex.ru
Project-URL: GitHub, https://github.com/DianaSadova/Graf
Keywords: graf,mathematics
Classifier: Programming Language :: Python :: 3.11
Classifier: License :: OSI Approved :: MIT License
Classifier: Operating System :: OS Independent
Requires-Python: >=3.6
License-File: LICENSE.txt
Requires-Dist: requests>=2.25.1
Requires-Dist: matplotlib==3.10.0
Requires-Dist: numpy==2.2.1
Requires-Dist: networkx==3.4.2
